dsg_lib/__init__.py
dsg_lib/async_database_functions/__import_sqlalchemy.py
dsg_lib/async_database_functions/__init__.py
dsg_lib/async_database_functions/async_database.py
dsg_lib/async_database_functions/base_schema.py
dsg_lib/async_database_functions/database_config.py
dsg_lib/async_database_functions/database_operations.py
dsg_lib/common_functions/__init__.py
dsg_lib/common_functions/calendar_functions.py
dsg_lib/common_functions/email_validation.py
dsg_lib/common_functions/file_functions.py
dsg_lib/common_functions/file_mover.py
dsg_lib/common_functions/folder_functions.py
dsg_lib/common_functions/logging_config.py
dsg_lib/common_functions/patterns.py
dsg_lib/fastapi_functions/__init__.py
dsg_lib/fastapi_functions/_all_codes.py
dsg_lib/fastapi_functions/default_endpoints.py
dsg_lib/fastapi_functions/http_codes.py
dsg_lib/fastapi_functions/system_health_endpoints.py
devsetgo_lib-2025.8.9.1.dist-info/METADATA
devsetgo_lib-2025.8.9.1.dist-info/WHEEL
devsetgo_lib-2025.8.9.1.dist-info/licenses/LICENSE
devsetgo_lib-2025.8.9.1.dist-info/RECORD
