Metadata-Version: 2.4
Name: devsetgo_lib
Version: 2025.8.9.1
Summary: DevSetGo Library is a Python library offering reusable functions for efficient coding. It includes file operations, calendar utilities, pattern matching, advanced logging with loguru, FastAPI endpoints, async database handling, and email validation. Designed for ease of use and versatility, it's a valuable tool for Python developers.
Project-URL: Homepage, https://github.com/devsetgo/devsetgo_lib
Project-URL: Documentation, https://devsetgo.github.io/devsetgo_lib/
Project-URL: Repository, https://github.com/devsetgo/devsetgo_lib
Author-email: Mike Ryan <mikeryan56@gmail.com>
Maintainer-email: Mike Ryan <mikeryan56@gmail.com>
License: MIT License
License-File: LICENSE
Keywords: CRUD operations,FastAPI,async database,calendar utilities,development tools,email validation,file operations,library,logging,loguru,pattern matching,python,reusable functions
Classifier: License :: OSI Approved :: MIT License
Classifier: Operating System :: MacOS :: MacOS X
Classifier: Operating System :: Microsoft :: Windows
Classifier: Operating System :: POSIX
Classifier: Operating System :: POSIX :: Linux
Classifier: Programming Language :: Python
Classifier: Programming Language :: Python :: 3
Classifier: Programming Language :: Python :: 3.9
Classifier: Programming Language :: Python :: 3.10
Classifier: Programming Language :: Python :: 3.11
Classifier: Programming Language :: Python :: 3.12
Requires-Python: >=3.10
Requires-Dist: email-validator>=2.1.1
Requires-Dist: loguru>=0.7.0
Requires-Dist: packaging>=22.0
Requires-Dist: watchfiles<1.1.1,>=1.0.1
Provides-Extra: all
Requires-Dist: aioodbc>=0.4.1; extra == 'all'
Requires-Dist: aiosqlite>=0.17.0; extra == 'all'
Requires-Dist: asyncmy>=0.2.10; extra == 'all'
Requires-Dist: asyncpg>=0.21.0; extra == 'all'
Requires-Dist: fastapi>=0.100.0; extra == 'all'
Requires-Dist: oracledb<2.5.0,>=2.4.1; extra == 'all'
Requires-Dist: pydantic[email]>=2.0; extra == 'all'
Requires-Dist: sqlalchemy-cockroachdb<3.0.0; extra == 'all'
Requires-Dist: sqlalchemy<2.0.99,>=2.0.10; extra == 'all'
Provides-Extra: cockroachdb
Requires-Dist: asyncpg>=0.21.0; extra == 'cockroachdb'
Requires-Dist: sqlalchemy-cockroachdb<2.0.4; extra == 'cockroachdb'
Requires-Dist: sqlalchemy<2.0.99,>=2.0.10; extra == 'cockroachdb'
Provides-Extra: fastapi
Requires-Dist: fastapi>=0.100.0; extra == 'fastapi'
Requires-Dist: pydantic[email]>=2.0; extra == 'fastapi'
Provides-Extra: mssql
Requires-Dist: aioodbc>=0.4.1; extra == 'mssql'
Requires-Dist: sqlalchemy<2.0.99,>=2.0.10; extra == 'mssql'
Provides-Extra: mysql
Requires-Dist: asyncmy>=0.2.10; extra == 'mysql'
Requires-Dist: sqlalchemy<2.0.99,>=2.0.10; extra == 'mysql'
Provides-Extra: oracle
Requires-Dist: oracledb<2.5.0,>=2.4.1; extra == 'oracle'
Requires-Dist: sqlalchemy<2.0.99,>=2.0.10; extra == 'oracle'
Provides-Extra: postgres
Requires-Dist: asyncpg>=0.21.0; extra == 'postgres'
Requires-Dist: sqlalchemy<2.0.99,>=2.0.10; extra == 'postgres'
Provides-Extra: sqlite
Requires-Dist: aiosqlite>=0.17.0; extra == 'sqlite'
Requires-Dist: sqlalchemy<2.0.99,>=2.0.10; extra == 'sqlite'
